CHANGELOG
COPYING
MANIFEST.in
README
TODO
array_test.py
op_loops.h
operations.h
setup.py
structarray.c
structarray.pxd
structarray.pyx
StructArray.egg-info/PKG-INFO
StructArray.egg-info/SOURCES.txt
StructArray.egg-info/dependency_links.txt
StructArray.egg-info/native_libs.txt
StructArray.egg-info/top_level.txt
docs/make_docs.py
docs/structarray/index.html
docs/structarray/Array/index.html
docs/structarray/StructArray/index.html
docs/templates/base.html
docs/templates/class.html
docs/templates/module.html
examples/particle.png
examples/particles.py
timeit/time_add_a_a.py
timeit/time_add_a_f.py
timeit/time_add_stretch_repeat.py
timeit/time_assign_to.py
timeit/time_div_a_a.py
timeit/time_index_attr_assign.py
timeit/time_index_tuple_assign.py
timeit/time_iter.py
timeit/time_iter_assign.py
