Metadata-Version: 1.0
Name: StructArray
Version: 0.1
Summary: Fast operations on arrays of structured data.
Home-page: http://matthewmarshall.org/projects/structarray/
Author: Matthew Marshall
Author-email: matthew@matthewmarshall.org
License: MIT
Platform: UNKNOWN
